Metadata-Version: 2.1
Name: vqapi
Version: 0.6.4.40
Summary: ViQi Python API
Author: ViQi Inc
Author-email: info@viqi.org
Project-URL: homepage, https://www.viqi.org
Classifier: Programming Language :: Python :: 3
Classifier: Programming Language :: Python :: 3.8
Classifier: Programming Language :: Python :: 3.10
Requires-Python: >=3.8
Requires-Dist: configparser
Requires-Dist: bisque-metadoc
Requires-Dist: tifffile
Requires-Dist: simplejson
Requires-Dist: shortuuid >=1.0.8
Requires-Dist: tenacity
Requires-Dist: requests-cache
Requires-Dist: requests-toolbelt
Requires-Dist: boto3
Requires-Dist: importlib-metadata ; python_version < "3.10"
Provides-Extra: image_service
Requires-Dist: tifffile ; extra == 'image_service'
Requires-Dist: tables ; extra == 'image_service'
Provides-Extra: table_service
Requires-Dist: numpy ; extra == 'table_service'
Requires-Dist: pandas ; extra == 'table_service'
Requires-Dist: tables ; extra == 'table_service'
